quicklink25/__init__.py
quicklink25/DOC/PRACTICAL NO 1.docx
quicklink25/DOC/PRACTICAL NO 10.docx
quicklink25/DOC/PRACTICAL NO 11.docx
quicklink25/DOC/PRACTICAL NO 2.docx
quicklink25/DOC/PRACTICAL NO 3.docx
quicklink25/DOC/PRACTICAL NO 4.docx
quicklink25/DOC/PRACTICAL NO 5.docx
quicklink25/DOC/PRACTICAL NO 6.docx
quicklink25/DOC/PRACTICAL NO 7.docx
quicklink25/DOC/PRACTICAL NO 8.docx
quicklink25/DOC/PRACTICAL NO 9.docx
quicklink25/MANUAL/AMP practical full.pdf
quicklink25/TEXT/quick.txt
quicklink25/TEXT/quick2.txt
quicklink25-0.1.dist-info/METADATA
quicklink25-0.1.dist-info/WHEEL
quicklink25-0.1.dist-info/top_level.txt
quicklink25-0.1.dist-info/RECORD
