Metadata-Version: 2.4
Name: quicklink25
Version: 0.1
Summary: A module with documents, data files, and scripts
Home-page: https://example.com/mymodule
Author: Your Name
Author-email: your.email@example.com
Dynamic: author
Dynamic: author-email
Dynamic: home-page
Dynamic: summary
